protspace/__init__.py
protspace/app.py
protspace/main.py
protspace/wsgi.py
protspace/assets/__init__.py
protspace/assets/annotated_image.png
protspace/assets/custom.css
protspace/assets/rostlab_logo.png
protspace/assets/help_content/__init__.py
protspace/assets/help_content/help_faq.md
protspace/assets/help_content/help_how_it_works.md
protspace/assets/help_content/help_json.md
protspace/assets/help_content/help_overview.md
protspace/cli/__init__.py
protspace/cli/common_args.py
protspace/cli/local_data.py
protspace/cli/uniprot_query.py
protspace/core/__init__.py
protspace/core/config.py
protspace/core/constants.py
protspace/data/__init__.py
protspace/data/base_data_processor.py
protspace/data/feature_manager.py
protspace/data/local_data_processor.py
protspace/data/uniprot_query_processor.py
protspace/data/feature_retrievers/__init__.py
protspace/data/feature_retrievers/interpro_feature_retriever.py
protspace/data/feature_retrievers/taxonomy_feature_retriever.py
protspace/data/feature_retrievers/uniprot_feature_retriever.py
protspace/ui/__init__.py
protspace/ui/callbacks.py
protspace/ui/layout.py
protspace/ui/styles.py
protspace/utils/__init__.py
protspace/utils/add_feature_style.py
protspace/utils/analyse_json.py
protspace/utils/arrow_reader.py
protspace/utils/json_reader.py
protspace/utils/reducers.py
protspace/visualization/__init__.py
protspace/visualization/molstar.py
protspace/visualization/plotting.py
protspace-3.0.0.dist-info/METADATA
protspace-3.0.0.dist-info/WHEEL
protspace-3.0.0.dist-info/entry_points.txt
protspace-3.0.0.dist-info/licenses/LICENSE
protspace-3.0.0.dist-info/RECORD
