Metadata-Version: 2.4
Name: protspace
Version: 3.0.0
Summary: A visualisation tool for protein embeddings from pLMs
Author-email: Tobias Senoner <tobias.senoner@tum.de>
License-Expression: GPL-3.0
License-File: LICENSE
Requires-Python: >=3.10
Requires-Dist: bioservices>=1.12.1
Requires-Dist: h5py>=3.12.1
Requires-Dist: matplotlib>=3.9.2
Requires-Dist: numpy>=1.23.0
Requires-Dist: pacmap>=0.8.0
Requires-Dist: pandas>=2.0.0
Requires-Dist: pyarrow>=20.0.0
Requires-Dist: pymmseqs>=1.0.4
Requires-Dist: scikit-learn>=1.6.1
Requires-Dist: taxopy>=0.14.0
Requires-Dist: tqdm>=4.67.1
Requires-Dist: umap-learn>=0.5.7
Provides-Extra: frontend
Requires-Dist: dash-bootstrap-components>=1.6.0; extra == 'frontend'
Requires-Dist: dash-daq>=0.5.0; extra == 'frontend'
Requires-Dist: dash-iconify>=0.1.2; extra == 'frontend'
Requires-Dist: dash-molstar>=1.3.0; extra == 'frontend'
Requires-Dist: dash>=3; extra == 'frontend'
Requires-Dist: gunicorn>=23.0.0; extra == 'frontend'
Requires-Dist: kaleido!=0.2.1.post1,>=0.2.1; extra == 'frontend'
Requires-Dist: plotly>=5.24.1; extra == 'frontend'
Requires-Dist: python-dotenv>=1.0.1; extra == 'frontend'
Requires-Dist: requests>=2.32.4; extra == 'frontend'
